rlearn/__init__.py
rlearn/board.py
rlearn/config.py
rlearn/transformer.py
rlearn/type.py
rlearn/distributed/__init__.py
rlearn/distributed/logger.py
rlearn/distributed/tools.py
rlearn/distributed/experience/__init__.py
rlearn/distributed/experience/actor.py
rlearn/distributed/experience/actor_pb2.py
rlearn/distributed/experience/actor_pb2_grpc.py
rlearn/distributed/experience/buffer.py
rlearn/distributed/experience/buffer_pb2.py
rlearn/distributed/experience/buffer_pb2_grpc.py
rlearn/distributed/experience/learner.py
rlearn/distributed/gradient/__init__.py
rlearn/distributed/gradient/param_pb2.py
rlearn/distributed/gradient/param_pb2_grpc.py
rlearn/distributed/gradient/param_server.py
rlearn/distributed/gradient/worker.py
rlearn/env/__init__.py
rlearn/env/env_wrapper.py
rlearn/model/__init__.py
rlearn/model/ac.py
rlearn/model/base.py
rlearn/model/ddpg.py
rlearn/model/dqn.py
rlearn/model/dueling_dqn.py
rlearn/model/ppo.py
rlearn/model/rnd.py
rlearn/model/sac.py
rlearn/model/td3.py
rlearn/model/tools.py
rlearn/replaybuf/__init__.py
rlearn/replaybuf/base.py
rlearn/replaybuf/prioritized_buf.py
rlearn/replaybuf/random_buf.py
rlearn/replaybuf/tools.py
rlearn/supervised/__init__.py
rlearn/trainer/__init__.py
rlearn/trainer/ac.py
rlearn/trainer/base.py
rlearn/trainer/ddpg.py
rlearn/trainer/dqn.py
rlearn/trainer/dueling_dqn.py
rlearn/trainer/map_fn.py
rlearn/trainer/ppo.py
rlearn/trainer/sac.py
rlearn/trainer/td3.py
rlearn/trainer/tools.py
rlearn/zoo/__init__.py
rlearn/zoo/dqn.py
rlearn_envs/__init__.py
rlearn_envs/maze/__init__.py
rlearn_envs/maze/load.py
rlearn_envs/maze/maze_env.py
rlearn-0.0.4.dist-info/LICENSE
rlearn-0.0.4.dist-info/METADATA
rlearn-0.0.4.dist-info/WHEEL
rlearn-0.0.4.dist-info/top_level.txt
rlearn-0.0.4.dist-info/RECORD
