Metadata-Version: 2.1
Name: rlearn
Version: 0.0.4
Summary: reinforcement learning algorithms in python
Home-page: https://git.woa.com/TIPE/rlearn
Author: MorvanZhou
Author-email: morvanzhou@hotmail.com
Project-URL: Bug Tracker, https://git.woa.com/TIPE/rlearn/issues
Project-URL: Source, https://git.woa.com/TIPE/rlearn
Classifier: Programming Language :: Python :: 3
Classifier: License :: OSI Approved :: MIT License
Classifier: Operating System :: OS Independent
Requires-Python: >=3.8
License-File: LICENSE
Requires-Dist: tensorflow-probability (<0.18.0,>=0.17.0)
Requires-Dist: tensorflow (<2.10,>=2.9.2) ; python_version >= "3.8" and platform_system == "Darwin" and platform_machine != "arm64"
Requires-Dist: tensorflow-macos (<2.10,==2.9.2) ; python_version >= "3.8" and platform_system == "Darwin" and platform_machine == "arm64"
Requires-Dist: tensorflow-metal (==0.5.0) ; python_version >= "3.8" and platform_system == "Darwin" and platform_machine == "arm64"
Requires-Dist: tensorflow-probability (<0.18.0,==0.17.0) ; python_version >= "3.8" and platform_system == "Darwin" and platform_machine == "arm64"
Requires-Dist: tensorflow (<2.10,>=2.9.2) ; python_version >= "3.8" and platform_system == "Linux"
Requires-Dist: tensorflow (<2.10,>=2.9.2) ; python_version >= "3.8" and platform_system == "Windows"
Provides-Extra: build
Requires-Dist: tox (==3.24.3) ; extra == 'build'
Requires-Dist: tox-conda ; extra == 'build'
Requires-Dist: build ; extra == 'build'
Requires-Dist: twine ; extra == 'build'
Requires-Dist: pylint ; extra == 'build'
Requires-Dist: grpcio-tools (>=1.42.0) ; (python_version >= "3.8") and extra == 'build'
Requires-Dist: grpcio-tools (>=1.42.0) ; (python_version >= "3.8" and platform_system == "Darwin" and platform_machine == "arm64") and extra == 'build'
Provides-Extra: envs
Requires-Dist: pygame (>=2.1.0) ; extra == 'envs'
Provides-Extra: test
Requires-Dist: gymnasium[classic_control] (>=0.27.1) ; extra == 'test'
